{
  "custom": {},
  "params": {},
  "props": {
    "defaultSize": {
      "height": 974,
      "width": 1855
    }
  },
  "root": {
    "children": [
      {
        "meta": {
          "name": "Header"
        },
        "position": {
          "basis": "70px",
          "shrink": 0
        },
        "props": {
          "path": "Participants/Dashboard/Cards/Participant_Header"
        },
        "type": "ia.display.view"
      },
      {
        "meta": {
          "name": "Label"
        },
        "position": {
          "basis": "32px",
          "display": false
        },
        "propConfig": {
          "props.text": {
            "binding": {
              "config": {
                "path": "page.props.pageId"
              },
              "type": "property"
            }
          }
        },
        "type": "ia.display.label"
      },
      {
        "meta": {
          "name": "Tabs"
        },
        "position": {
          "basis": "892px",
          "grow": 1
        },
        "props": {
          "path": "Participants/Dashboard/Cards/Participant_Tabs"
        },
        "type": "ia.display.view"
      }
    ],
    "meta": {
      "name": "root"
    },
    "props": {
      "direction": "column",
      "style": {
        "overflow": "hidden"
      }
    },
    "type": "ia.container.flex"
  }
}